[{"Ticker":"7054.KL","Code":"7054","Name":"AASIA","Sector":"Plantation","Sector Abbrev":"PLT"},{"Ticker":"7167.KL","Code":"7167","Name":"ABLEGLOB","Sector":"Consumer Products & Services","Sector Abbrev":"CON"},{"Ticker":"7086.KL","Code":"7086","Name":"ABLEGRP","Sector":"Industrial Products & Services","Sector Abbrev":"IND"},{"Ticker":"7131.KL","Code":"7131","Name":"ACME","Sector":"Property","Sector Abbrev":"PRP"},{"Ticker":"0218.KL","Code":"0218","Name":"ACO","Sector":"Industrial Products & Services","Sector Abbrev":"IND"},{"Ticker":"7191.KL","Code":"7191","Name":"ADVENTA","Sector":"Health Care","Sector Abbrev":"HLT"},{"Ticker":"7146.KL","Code":"7146","Name":"AEM","Sector":"Industrial Products & Services","Sector Abbrev":"IND"},{"Ticker":"5198.KL","Code":"5198","Name":"AFUJIYA","Sector":"Industrial Products & Services","Sector Abbrev":"IND"},{"Ticker":"7315.KL","Code":"7315","Name":"AHB","Sector":"Consumer Products & Services","Sector Abbrev":"CON"},{"Ticker":"7219.KL","Code":"7219","Name":"AIZO","Sector":"Industrial Products & Services","Sector Abbrev":"IND"},{"Ticker":"7609.KL","Code":"7609","Name":"AJIYA","Sector":"Industrial Products & Services","Sector Abbrev":"IND"},{"Ticker":"2674.KL","Code":"2674","Name":"ALCOM","Sector":"Industrial Products & Services","Sector Abbrev":"IND"},{"Ticker":"7031.KL","Code":"7031","Name":"AMTEL","Sector":"Telecommunications & Media","Sector Abbrev":"TEL"},{"Ticker":"7083.KL","Code":"7083","Name":"ANALABS","Sector":"Industrial Products & Services","Sector Abbrev":"IND"},{"Ticker":"4758.KL","Code":"4758","Name":"ANCOMNY","Sector":"Industrial Products & Services","Sector Abbrev":"IND"},{"Ticker":"5568.KL","Code":"5568","Name":"APB","Sector":"Industrial Products & Services","Sector Abbrev":"IND"},{"Ticker":"7214.KL","Code":"7214","Name":"ARANK","Sector":"Industrial Products & Services","Sector Abbrev":"IND"},{"Ticker":"7181.KL","Code":"7181","Name":"ARBB","Sector":"Industrial Products & Services","Sector Abbrev":"IND"},{"Ticker":"7007.KL","Code":"7007","Name":"ARK","Sector":"Property","Sector Abbrev":"PRP"},{"Ticker":"7218.KL","Code":"7218","Name":"ARKA","Sector":"Trading Services","Sector Abbrev":"TRD"},{"Ticker":"1481.KL","Code":"1481","Name":"ASB","Sector":"Consumer Products & Services","Sector Abbrev":"CON"},{"Ticker":"4057.KL","Code":"4057","Name":"ASIAPAC","Sector":"Property","Sector Abbrev":"PRP"},{"Ticker":"7020.KL","Code":"7020","Name":"ASTEEL","Sector":"Industrial Products & Services","Sector Abbrev":"IND"},{"Ticker":"7162.KL","Code":"7162","Name":"ASTINO","Sector":"Industrial Products & Services","Sector Abbrev":"IND"},{"Ticker":"5130.KL","Code":"5130","Name":"ATRIUM","Sector":"REIT","Sector Abbrev":"REI"},{"Ticker":"5025.KL","Code":"5025","Name":"AURO","Sector":"Industrial Products & Services","Sector Abbrev":"IND"},{"Ticker":"7579.KL","Code":"7579","Name":"AWC","Sector":"Industrial Products & Services","Sector Abbrev":"IND"},{"Ticker":"7120.KL","Code":"7120","Name":"AXTERIA","Sector":"Consumer Products & Services","Sector Abbrev":"CON"},{"Ticker":"5021.KL","Code":"5021","Name":"AYS","Sector":"Industrial Products & Services","Sector Abbrev":"IND"},{"Ticker":"6602.KL","Code":"6602","Name":"BCB","Sector":"Property","Sector Abbrev":"PRP"},{"Ticker":"6173.KL","Code":"6173","Name":"BDB","Sector":"Property","Sector Abbrev":"PRP"},{"Ticker":"6378.KL","Code":"6378","Name":"BEDI","Sector":"Property","Sector Abbrev":"PRP"},{"Ticker":"9814.KL","Code":"9814","Name":"BERTAM","Sector":"Property","Sector Abbrev":"PRP"},{"Ticker":"7005.KL","Code":"7005","Name":"BIG","Sector":"Industrial Products & Services","Sector Abbrev":"IND"},{"Ticker":"6998.KL","Code":"6998","Name":"BINTAI","Sector":"Industrial Products & Services","Sector Abbrev":"IND"},{"Ticker":"7195.KL","Code":"7195","Name":"BNASTRA","Sector":"Industrial Products & Services","Sector Abbrev":"IND"},{"Ticker":"7036.KL","Code":"7036","Name":"BORNOIL","Sector":"Industrial Products & Services","Sector Abbrev":"IND"},{"Ticker":"6297.KL","Code":"6297","Name":"BOXPAK","Sector":"Industrial Products & Services","Sector Abbrev":"IND"},{"Ticker":"5100.KL","Code":"5100","Name":"BPPLAS","Sector":"Industrial Products & Services","Sector Abbrev":"IND"},{"Ticker":"5932.KL","Code":"5932","Name":"BPURI","Sector":"Construction","Sector Abbrev":"CST"},{"Ticker":"9938.KL","Code":"9938","Name":"BRIGHT","Sector":"Industrial Products & Services","Sector Abbrev":"IND"},{"Ticker":"7221.KL","Code":"7221","Name":"BSLCORP","Sector":"Industrial Products & Services","Sector Abbrev":"IND"},{"Ticker":"7188.KL","Code":"7188","Name":"BTM","Sector":"Industrial Products & Services","Sector Abbrev":"IND"},{"Ticker":"7174.KL","Code":"7174","Name":"CAB","Sector":"Consumer Products & Services","Sector Abbrev":"CON"},{"Ticker":"7128.KL","Code":"7128","Name":"CAMRES","Sector":"Consumer Products & Services","Sector Abbrev":"CON"},{"Ticker":"7035.KL","Code":"7035","Name":"CCK","Sector":"Consumer Products & Services","Sector Abbrev":"CON"},{"Ticker":"8435.KL","Code":"8435","Name":"CEPCO","Sector":"Industrial Products & Services","Sector Abbrev":"IND"},{"Ticker":"8044.KL","Code":"8044","Name":"CFM","Sector":"Industrial Products & Services","Sector Abbrev":"IND"},{"Ticker":"8052.KL","Code":"8052","Name":"CGB","Sector":"Industrial Products & Services","Sector Abbrev":"IND"},{"Ticker":"7209.KL","Code":"7209","Name":"CHEETAH","Sector":"Consumer Products & Services","Sector Abbrev":"CON"},{"Ticker":"7187.KL","Code":"7187","Name":"CHGP","Sector":"Transportation & Logistics","Sector Abbrev":"TRN"},{"Ticker":"5797.KL","Code":"5797","Name":"CHOOBEE","Sector":"Industrial Products & Services","Sector Abbrev":"IND"},{"Ticker":"7016.KL","Code":"7016","Name":"CHUAN","Sector":"Industrial Products & Services","Sector Abbrev":"IND"},{"Ticker":"2828.KL","Code":"2828","Name":"CIHLDG","Sector":"Consumer Products & Services","Sector Abbrev":"CON"},{"Ticker":"7245.KL","Code":"7245","Name":"CITAGLB","Sector":"Industrial Products & Services","Sector Abbrev":"IND"},{"Ticker":"7018.KL","Code":"7018","Name":"CME","Sector":"Industrial Products & Services","Sector Abbrev":"IND"},{"Ticker":"7986.KL","Code":"7986","Name":"CNASIA","Sector":"Industrial Products & Services","Sector Abbrev":"IND"},{"Ticker":"5104.KL","Code":"5104","Name":"CNH","Sector":"Consumer Products & Services","Sector Abbrev":"CON"},{"Ticker":"5188.KL","Code":"5188","Name":"CNOUHUA","Sector":"Consumer Products & Services","Sector Abbrev":"CON"},{"Ticker":"2127.KL","Code":"2127","Name":"COMFORT","Sector":"Industrial Products & Services","Sector Abbrev":"IND"},{"Ticker":"5037.KL","Code":"5037","Name":"COMPUGT","Sector":"Industrial Products & Services","Sector Abbrev":"IND"},{"Ticker":"8591.KL","Code":"8591","Name":"CRESBLD","Sector":"Construction","Sector Abbrev":"CST"},{"Ticker":"0051.KL","Code":"0051","Name":"CUSCAPI","Sector":"Technology","Sector Abbrev":"TEC"},{"Ticker":"5049.KL","Code":"5049","Name":"CVIEW","Sector":"Property","Sector Abbrev":"PRP"},{"Ticker":"9423.KL","Code":"9423","Name":"CWG","Sector":"Consumer Products & Services","Sector Abbrev":"CON"},{"Ticker":"7157.KL","Code":"7157","Name":"CYL","Sector":"Industrial Products & Services","Sector Abbrev":"IND"},{"Ticker":"8338.KL","Code":"8338","Name":"DATAPRP","Sector":"Technology","Sector Abbrev":"TEC"},{"Ticker":"5165.KL","Code":"5165","Name":"DFCITY","Sector":"Industrial Products & Services","Sector Abbrev":"IND"},{"Ticker":"0029.KL","Code":"0029","Name":"DIGISTA","Sector":"Technology","Sector Abbrev":"TEC"},{"Ticker":"7528.KL","Code":"7528","Name":"DKLS","Sector":"Construction","Sector Abbrev":"CST"},{"Ticker":"7114.KL","Code":"7114","Name":"DNONCE","Sector":"Industrial Products & Services","Sector Abbrev":"IND"},{"Ticker":"7169.KL","Code":"7169","Name":"DOMINAN","Sector":"Industrial Products & Services","Sector Abbrev":"IND"},{"Ticker":"7198.KL","Code":"7198","Name":"DPS","Sector":"Property","Sector Abbrev":"PRP"},{"Ticker":"7233.KL","Code":"7233","Name":"DUFU","Sector":"Industrial Products & Services","Sector Abbrev":"IND"},{"Ticker":"5192.KL","Code":"5192","Name":"KSSC","Sector":"Industrial Products & Services","Sector Abbrev":"IND"},{"Ticker":"3557.KL","Code":"3557","Name":"ECOFIRS","Sector":"Property","Sector Abbrev":"PRP"},{"Ticker":"5036.KL","Code":"5036","Name":"EDARAN","Sector":"Technology","Sector Abbrev":"TEC"},{"Ticker":"7471.KL","Code":"7471","Name":"EDEN","Sector":"Trading Services","Sector Abbrev":"TRD"},{"Ticker":"0064.KL","Code":"0064","Name":"EFFICEN","Sector":"Industrial Products & Services","Sector Abbrev":"IND"},{"Ticker":"0065.KL","Code":"0065","Name":"EFORCE","Sector":"Technology","Sector Abbrev":"TEC"},{"Ticker":"0227.KL","Code":"0227","Name":"EFRAME","Sector":"Industrial Products & Services","Sector Abbrev":"IND"},{"Ticker":"8907.KL","Code":"8907","Name":"EG","Sector":"Industrial Products & Services","Sector Abbrev":"IND"},{"Ticker":"5081.KL","Code":"5081","Name":"EIG","Sector":"Consumer Products & Services","Sector Abbrev":"CON"},{"Ticker":"5208.KL","Code":"5208","Name":"EITA","Sector":"Industrial Products & Services","Sector Abbrev":"IND"},{"Ticker":"9016.KL","Code":"9016","Name":"EKSONS","Sector":"Industrial Products & Services","Sector Abbrev":"IND"},{"Ticker":"5228.KL","Code":"5228","Name":"ELKDESA","Sector":"Financial Services","Sector Abbrev":"FIN"},{"Ticker":"7217.KL","Code":"7217","Name":"EMETALL","Sector":"Industrial Products & Services","Sector Abbrev":"IND"},{"Ticker":"9091.KL","Code":"9091","Name":"EMICO","Sector":"Consumer Products & Services","Sector Abbrev":"CON"},{"Ticker":"7149.KL","Code":"7149","Name":"ENGKAH","Sector":"Consumer Products & Services","Sector Abbrev":"CON"},{"Ticker":"8613.KL","Code":"8613","Name":"ENRA","Sector":"Property","Sector Abbrev":"PRP"},{"Ticker":"4847.KL","Code":"4847","Name":"EPICON","Sector":"Consumer Products & Services","Sector Abbrev":"CON"},{"Ticker":"7773.KL","Code":"7773","Name":"EPMB","Sector":"Industrial Products & Services","Sector Abbrev":"IND"},{"Ticker":"9946.KL","Code":"9946","Name":"ETA","Sector":"Consumer Products & Services","Sector Abbrev":"CON"},{"Ticker":"6815.KL","Code":"6815","Name":"EUPE","Sector":"Property","Sector Abbrev":"PRP"},{"Ticker":"7208.KL","Code":"7208","Name":"EURO","Sector":"Consumer Products & Services","Sector Abbrev":"CON"},{"Ticker":"7094.KL","Code":"7094","Name":"EUROSP","Sector":"Consumer Products & Services","Sector Abbrev":"CON"},{"Ticker":"5101.KL","Code":"5101","Name":"EVERGRN","Sector":"Industrial Products & Services","Sector Abbrev":"IND"},{"Ticker":"1287.KL","Code":"1287","Name":"EXSIMHB","Sector":"Consumer Products & Services","Sector Abbrev":"CON"},{"Ticker":"2984.KL","Code":"2984","Name":"FACBIND","Sector":"Industrial Products & Services","Sector Abbrev":"IND"},{"Ticker":"6041.KL","Code":"6041","Name":"FARLIM","Sector":"Property","Sector Abbrev":"PRP"},{"Ticker":"2755.KL","Code":"2755","Name":"FCW","Sector":"Consumer Products & Services","Sector Abbrev":"CON"},{"Ticker":"6939.KL","Code":"6939","Name":"FIAMMA","Sector":"Consumer Products & Services","Sector Abbrev":"CON"},{"Ticker":"0149.KL","Code":"0149","Name":"FIBON","Sector":"Industrial Products & Services","Sector Abbrev":"IND"},{"Ticker":"8605.KL","Code":"8605","Name":"FIHB","Sector":"Consumer Products & Services","Sector Abbrev":"CON"},{"Ticker":"5197.KL","Code":"5197","Name":"FLBHD","Sector":"Industrial Products & Services","Sector Abbrev":"IND"},{"Ticker":"7210.KL","Code":"7210","Name":"FM","Sector":"Trading Services","Sector Abbrev":"TRD"},{"Ticker":"9172.KL","Code":"9172","Name":"FPI","Sector":"Consumer Products & Services","Sector Abbrev":"CON"},{"Ticker":"0128.KL","Code":"0128","Name":"FRONTKN","Sector":"Technology","Sector Abbrev":"TEC"},{"Ticker":"9377.KL","Code":"9377","Name":"FSBM","Sector":"Technology","Sector Abbrev":"TEC"},{"Ticker":"7184.KL","Code":"7184","Name":"G3","Sector":"Consumer Products & Services","Sector Abbrev":"CON"},{"Ticker":"9148.KL","Code":"9148","Name":"GBAY","Sector":"Industrial Products & Services","Sector Abbrev":"IND"},{"Ticker":"7676.KL","Code":"7676","Name":"GCAP","Sector":"Trading Services","Sector Abbrev":"TRD"},{"Ticker":"5592.KL","Code":"5592","Name":"GCE","Sector":"Consumer Products & Services","Sector Abbrev":"CON"},{"Ticker":"7197.KL","Code":"7197","Name":"GESHEN","Sector":"Industrial Products & Services","Sector Abbrev":"IND"},{"Ticker":"7192.KL","Code":"7192","Name":"GIIB","Sector":"Industrial Products & Services","Sector Abbrev":"IND"},{"Ticker":"7382.KL","Code":"7382","Name":"GLBHD","Sector":"Plantation","Sector Abbrev":"PLT"},{"Ticker":"9962.KL","Code":"9962","Name":"GMUTUAL","Sector":"Property","Sector Abbrev":"PRP"},{"Ticker":"2135.KL","Code":"2135","Name":"GOPENG","Sector":"Plantation","Sector Abbrev":"PLT"},{"Ticker":"5649.KL","Code":"5649","Name":"GPHAROS","Sector":"Industrial Products & Services","Sector Abbrev":"IND"},{"Ticker":"7943.KL","Code":"7943","Name":"GREENTEC","Sector":"Consumer Products & Services","Sector Abbrev":"CON"},{"Ticker":"0136.KL","Code":"0136","Name":"GREENYB","Sector":"Consumer Products & Services","Sector Abbrev":"CON"},{"Ticker":"5008.KL","Code":"5008","Name":"HARISON","Sector":"Consumer Products & Services","Sector Abbrev":"CON"},{"Ticker":"7501.KL","Code":"7501","Name":"HARNLEN","Sector":"Plantation","Sector Abbrev":"PLT"},{"Ticker":"5187.KL","Code":"5187","Name":"HBGLOB","Sector":"Consumer Products & Services","Sector Abbrev":"CON"},{"Ticker":"7105.KL","Code":"7105","Name":"HCK","Sector":"Property","Sector Abbrev":"PRP"},{"Ticker":"5095.KL","Code":"5095","Name":"HEVEA","Sector":"Industrial Products & Services","Sector Abbrev":"IND"},{"Ticker":"7803.KL","Code":"7803","Name":"HEXCARE","Sector":"Industrial Products & Services","Sector Abbrev":"IND"},{"Ticker":"7202.KL","Code":"7202","Name":"HEXRTL","Sector":"Consumer Products & Services","Sector Abbrev":"CON"},{"Ticker":"5151.KL","Code":"5151","Name":"HEXTAR","Sector":"Industrial Products & Services","Sector Abbrev":"IND"},{"Ticker":"5136.KL","Code":"5136","Name":"HEXTECH","Sector":"Trading Services","Sector Abbrev":"TRD"},{"Ticker":"3298.KL","Code":"3298","Name":"HEXZA","Sector":"Industrial Products & Services","Sector Abbrev":"IND"},{"Ticker":"7033.KL","Code":"7033","Name":"HIGHTEC","Sector":"Industrial Products & Services","Sector Abbrev":"IND"},{"Ticker":"8443.KL","Code":"8443","Name":"HIL","Sector":"Industrial Products & Services","Sector Abbrev":"IND"},{"Ticker":"5169.KL","Code":"5169","Name":"HOHUP","Sector":"Construction","Sector Abbrev":"CST"},{"Ticker":"5160.KL","Code":"5160","Name":"HOMERIZ","Sector":"Consumer Products & Services","Sector Abbrev":"CON"},{"Ticker":"0041.KL","Code":"0041","Name":"HONGSENG","Sector":"Technology","Sector Abbrev":"TEC"},{"Ticker":"0228.KL","Code":"0228","Name":"HPPHB","Sector":"Industrial Products & Services","Sector Abbrev":"IND"},{"Ticker":"5028.KL","Code":"5028","Name":"HTPADU","Sector":"Technology","Sector Abbrev":"TEC"},{"Ticker":"5000.KL","Code":"5000","Name":"HUMEIND","Sector":"Industrial Products & Services","Sector Abbrev":"IND"},{"Ticker":"8478.KL","Code":"8478","Name":"HWATAI","Sector":"Consumer Products & Services","Sector Abbrev":"CON"},{"Ticker":"9601.KL","Code":"9601","Name":"HWGB","Sector":"Industrial Products & Services","Sector Abbrev":"IND"},{"Ticker":"5084.KL","Code":"5084","Name":"IBRACO","Sector":"Property","Sector Abbrev":"PRP"},{"Ticker":"9113.KL","Code":"9113","Name":"ICONIC","Sector":"Consumer Products & Services","Sector Abbrev":"CON"},{"Ticker":"9687.KL","Code":"9687","Name":"IDEAL","Sector":"Property","Sector Abbrev":"PRP"},{"Ticker":"7240.KL","Code":"7240","Name":"IHB","Sector":"Consumer Products & Services","Sector Abbrev":"CON"},{"Ticker":"7222.KL","Code":"7222","Name":"IMASPRO","Sector":"Industrial Products & Services","Sector Abbrev":"IND"},{"Ticker":"5178.KL","Code":"5178","Name":"INGENIEU","Sector":"Industrial Products & Services","Sector Abbrev":"IND"},{"Ticker":"5107.KL","Code":"5107","Name":"IQGROUP","Sector":"Consumer Products & Services","Sector Abbrev":"CON"},{"Ticker":"9393.KL","Code":"9393","Name":"ITRONIC","Sector":"Technology","Sector Abbrev":"TEC"},{"Ticker":"7223.KL","Code":"7223","Name":"JADI","Sector":"Consumer Products & Services","Sector Abbrev":"CON"},{"Ticker":"8648.KL","Code":"8648","Name":"JASKITA","Sector":"Industrial Products & Services","Sector Abbrev":"IND"},{"Ticker":"7152.KL","Code":"7152","Name":"JAYCORP","Sector":"Consumer Products & Services","Sector Abbrev":"CON"},{"Ticker":"9083.KL","Code":"9083","Name":"JETSON","Sector":"Industrial Products & Services","Sector Abbrev":"IND"},{"Ticker":"8923.KL","Code":"8923","Name":"JIANKUN","Sector":"Property","Sector Abbrev":"PRP"},{"Ticker":"6769.KL","Code":"6769","Name":"JKGLAND","Sector":"Property","Sector Abbrev":"PRP"},{"Ticker":"7096.KL","Code":"7096","Name":"JOE","Sector":"Industrial Products & Services","Sector Abbrev":"IND"},{"Ticker":"3441.KL","Code":"3441","Name":"JOHAN","Sector":"Financial Services","Sector Abbrev":"FIN"},{"Ticker":"5673.KL","Code":"5673","Name":"JSB","Sector":"Industrial Products & Services","Sector Abbrev":"IND"},{"Ticker":"8672.KL","Code":"8672","Name":"KAMDAR","Sector":"Consumer Products & Services","Sector Abbrev":"CON"},{"Ticker":"0054.KL","Code":"0054","Name":"KARYON","Sector":"Industrial Products & Services","Sector Abbrev":"IND"},{"Ticker":"7216.KL","Code":"7216","Name":"KAWAN","Sector":"Consumer Products & Services","Sector Abbrev":"CON"},{"Ticker":"7199.KL","Code":"7199","Name":"KEINHIN","Sector":"Industrial Products & Services","Sector Abbrev":"IND"},{"Ticker":"7323.KL","Code":"7323","Name":"KEN","Sector":"Property","Sector Abbrev":"PRP"},{"Ticker":"7161.KL","Code":"7161","Name":"KERJAYA","Sector":"Construction","Sector Abbrev":"CST"},{"Ticker":"9334.KL","Code":"9334","Name":"KESM","Sector":"Technology","Sector Abbrev":"TEC"},{"Ticker":"0143.KL","Code":"0143","Name":"KEYASIC","Sector":"Technology","Sector Abbrev":"TEC"},{"Ticker":"0151.KL","Code":"0151","Name":"KGB","Sector":"Industrial Products & Services","Sector Abbrev":"IND"},{"Ticker":"6203.KL","Code":"6203","Name":"KHEESAN","Sector":"Consumer Products & Services","Sector Abbrev":"CON"},{"Ticker":"7062.KL","Code":"7062","Name":"KHIND","Sector":"Consumer Products & Services","Sector Abbrev":"CON"},{"Ticker":"6211.KL","Code":"6211","Name":"KIALIM","Sector":"Industrial Products & Services","Sector Abbrev":"IND"},{"Ticker":"5371.KL","Code":"5371","Name":"KIMHIN","Sector":"Industrial Products & Services","Sector Abbrev":"IND"},{"Ticker":"2453.KL","Code":"2453","Name":"KLUANG","Sector":"Plantation","Sector Abbrev":"PLT"},{"Ticker":"5035.KL","Code":"5035","Name":"KNUSFOR","Sector":"Industrial Products & Services","Sector Abbrev":"IND"},{"Ticker":"6971.KL","Code":"6971","Name":"KOBAY","Sector":"Industrial Products & Services","Sector Abbrev":"IND"},{"Ticker":"7017.KL","Code":"7017","Name":"KOMARK","Sector":"Industrial Products & Services","Sector Abbrev":"IND"},{"Ticker":"0002.KL","Code":"0002","Name":"KOTRA","Sector":"Health Care","Sector Abbrev":"HLT"},{"Ticker":"7077.KL","Code":"7077","Name":"KPPROP","Sector":"Property","Sector Abbrev":"PRP"},{"Ticker":"9121.KL","Code":"9121","Name":"KPSCB","Sector":"Industrial Products & Services","Sector Abbrev":"IND"},{"Ticker":"8362.KL","Code":"8362","Name":"KYM","Sector":"Industrial Products & Services","Sector Abbrev":"IND"},{"Ticker":"7179.KL","Code":"7179","Name":"LAGENDA","Sector":"Consumer Products & Services","Sector Abbrev":"CON"},{"Ticker":"9385.KL","Code":"9385","Name":"LAYHONG","Sector":"Consumer Products & Services","Sector Abbrev":"CON"},{"Ticker":"9326.KL","Code":"9326","Name":"LBALUM","Sector":"Industrial Products & Services","Sector Abbrev":"IND"},{"Ticker":"8494.KL","Code":"8494","Name":"LBICAP","Sector":"Property","Sector Abbrev":"PRP"},{"Ticker":"9628.KL","Code":"9628","Name":"LEBTECH","Sector":"Construction","Sector Abbrev":"CST"},{"Ticker":"8079.KL","Code":"8079","Name":"LEESK","Sector":"Consumer Products & Services","Sector Abbrev":"CON"},{"Ticker":"5232.KL","Code":"5232","Name":"LEONFB","Sector":"Industrial Products & Services","Sector Abbrev":"IND"},{"Ticker":"7170.KL","Code":"7170","Name":"LFECORP","Sector":"Industrial Products & Services","Sector Abbrev":"IND"},{"Ticker":"3573.KL","Code":"3573","Name":"LIENHOE","Sector":"Property","Sector Abbrev":"PRP"},{"Ticker":"7089.KL","Code":"7089","Name":"LIIHEN","Sector":"Consumer Products & Services","Sector Abbrev":"CON"},{"Ticker":"8486.KL","Code":"8486","Name":"LIONPSIM","Sector":"Industrial Products & Services","Sector Abbrev":"IND"},{"Ticker":"8303.KL","Code":"8303","Name":"LOTUS","Sector":"Consumer Products & Services","Sector Abbrev":"CON"},{"Ticker":"7234.KL","Code":"7234","Name":"LOTUSCIR","Sector":"Consumer Products & Services","Sector Abbrev":"CON"},{"Ticker":"9881.KL","Code":"9881","Name":"LSTEEL","Sector":"Industrial Products & Services","Sector Abbrev":"IND"},{"Ticker":"7085.KL","Code":"7085","Name":"LTKM","Sector":"Consumer Products & Services","Sector Abbrev":"CON"},{"Ticker":"5068.KL","Code":"5068","Name":"LUSTER","Sector":"Industrial Products & Services","Sector Abbrev":"IND"},{"Ticker":"5143.KL","Code":"5143","Name":"LUXCHEM","Sector":"Industrial Products & Services","Sector Abbrev":"IND"},{"Ticker":"9199.KL","Code":"9199","Name":"LYSAGHT","Sector":"Industrial Products & Services","Sector Abbrev":"IND"},{"Ticker":"7082.KL","Code":"7082","Name":"MA","Sector":"Consumer Products & Services","Sector Abbrev":"CON"},{"Ticker":"7243.KL","Code":"7243","Name":"MAGMA","Sector":"Consumer Products & Services","Sector Abbrev":"CON"},{"Ticker":"3514.KL","Code":"3514","Name":"MARCO","Sector":"Consumer Products & Services","Sector Abbrev":"CON"},{"Ticker":"7029.KL","Code":"7029","Name":"MASTER","Sector":"Industrial Products & Services","Sector Abbrev":"IND"},{"Ticker":"4022.KL","Code":"4022","Name":"MAXIM","Sector":"Property","Sector Abbrev":"PRP"},{"Ticker":"7123.KL","Code":"7123","Name":"MAXLAND","Sector":"Industrial Products & Services","Sector Abbrev":"IND"},{"Ticker":"7099.KL","Code":"7099","Name":"MAYU","Sector":"Industrial Products & Services","Sector Abbrev":"IND"},{"Ticker":"5152.KL","Code":"5152","Name":"MBL","Sector":"Industrial Products & Services","Sector Abbrev":"IND"},{"Ticker":"2097.KL","Code":"2097","Name":"MBRIGHT","Sector":"Consumer Products & Services","Sector Abbrev":"CON"},{"Ticker":"7004.KL","Code":"7004","Name":"MCEHLDG","Sector":"Industrial Products & Services","Sector Abbrev":"IND"},{"Ticker":"5129.KL","Code":"5129","Name":"MELATI","Sector":"Construction","Sector Abbrev":"CST"},{"Ticker":"3778.KL","Code":"3778","Name":"MELEWAR","Sector":"Industrial Products & Services","Sector Abbrev":"IND"},{"Ticker":"1694.KL","Code":"1694","Name":"MENANG","Sector":"Property","Sector Abbrev":"PRP"},{"Ticker":"5223.KL","Code":"5223","Name":"MENTIGA","Sector":"Property","Sector Abbrev":"PRP"},{"Ticker":"8192.KL","Code":"8192","Name":"MERCURY","Sector":"Construction","Sector Abbrev":"CST"},{"Ticker":"6149.KL","Code":"6149","Name":"METROD","Sector":"Industrial Products & Services","Sector Abbrev":"IND"},{"Ticker":"5001.KL","Code":"5001","Name":"MIECO","Sector":"Industrial Products & Services","Sector Abbrev":"IND"},{"Ticker":"7935.KL","Code":"7935","Name":"MILUX","Sector":"Consumer Products & Services","Sector Abbrev":"CON"},{"Ticker":"5576.KL","Code":"5576","Name":"MINHO","Sector":"Industrial Products & Services","Sector Abbrev":"IND"},{"Ticker":"8141.KL","Code":"8141","Name":"MJPERAK","Sector":"Property","Sector Abbrev":"PRP"},{"Ticker":"5011.KL","Code":"5011","Name":"MSNIAGA","Sector":"Technology","Sector Abbrev":"TEC"},{"Ticker":"0043.KL","Code":"0043","Name":"MTRONIC","Sector":"Industrial Products & Services","Sector Abbrev":"IND"},{"Ticker":"9539.KL","Code":"9539","Name":"MUH","Sector":"Property","Sector Abbrev":"PRP"},{"Ticker":"3913.KL","Code":"3913","Name":"MUIPROP","Sector":"Property","Sector Abbrev":"PRP"},{"Ticker":"5087.KL","Code":"5087","Name":"MYCRON","Sector":"Industrial Products & Services","Sector Abbrev":"IND"},{"Ticker":"7692.KL","Code":"7692","Name":"MYTECH","Sector":"Industrial Products & Services","Sector Abbrev":"IND"},{"Ticker":"0056.KL","Code":"0056","Name":"NCT","Sector":"Technology","Sector Abbrev":"TEC"},{"Ticker":"7154.KL","Code":"7154","Name":"NEXGBINA","Sector":"Consumer Products & Services","Sector Abbrev":"CON"},{"Ticker":"7241.KL","Code":"7241","Name":"NGGB","Sector":"Industrial Products & Services","Sector Abbrev":"IND"},{"Ticker":"5614.KL","Code":"5614","Name":"NHB","Sector":"Trading Services","Sector Abbrev":"TRD"},{"Ticker":"7060.KL","Code":"7060","Name":"NHFATT","Sector":"Consumer Products & Services","Sector Abbrev":"CON"},{"Ticker":"7139.KL","Code":"7139","Name":"NICE","Sector":"Consumer Products & Services","Sector Abbrev":"CON"},{"Ticker":"7215.KL","Code":"7215","Name":"NIHSIN","Sector":"Consumer Products & Services","Sector Abbrev":"CON"},{"Ticker":"5533.KL","Code":"5533","Name":"OCB","Sector":"Consumer Products & Services","Sector Abbrev":"CON"},{"Ticker":"7071.KL","Code":"7071","Name":"OCR","Sector":"Construction","Sector Abbrev":"CST"},{"Ticker":"7107.KL","Code":"7107","Name":"OFI","Sector":"Consumer Products & Services","Sector Abbrev":"CON"},{"Ticker":"5827.KL","Code":"5827","Name":"OIB","Sector":"Property","Sector Abbrev":"PRP"},{"Ticker":"7140.KL","Code":"7140","Name":"OKA","Sector":"Industrial Products & Services","Sector Abbrev":"IND"},{"Ticker":"5079.KL","Code":"5079","Name":"ONEGLOVE","Sector":"Consumer Products & Services","Sector Abbrev":"CON"},{"Ticker":"5065.KL","Code":"5065","Name":"ORNA","Sector":"Industrial Products & Services","Sector Abbrev":"IND"},{"Ticker":"7225.KL","Code":"7225","Name":"PA","Sector":"Industrial Products & Services","Sector Abbrev":"IND"},{"Ticker":"8419.KL","Code":"8419","Name":"PANSAR","Sector":"Industrial Products & Services","Sector Abbrev":"IND"},{"Ticker":"5022.KL","Code":"5022","Name":"PAOS","Sector":"Consumer Products & Services","Sector Abbrev":"CON"},{"Ticker":"9407.KL","Code":"9407","Name":"PARAGON","Sector":"Consumer Products & Services","Sector Abbrev":"CON"},{"Ticker":"2682.KL","Code":"2682","Name":"PARKWD","Sector":"Industrial Products & Services","Sector Abbrev":"IND"},{"Ticker":"6912.KL","Code":"6912","Name":"PASDEC","Sector":"Property","Sector Abbrev":"PRP"},{"Ticker":"6068.KL","Code":"6068","Name":"PCCS","Sector":"Consumer Products & Services","Sector Abbrev":"CON"},{"Ticker":"6254.KL","Code":"6254","Name":"PDZ","Sector":"Trading Services","Sector Abbrev":"TRD"},{"Ticker":"5622.KL","Code":"5622","Name":"PEB","Sector":"Construction","Sector Abbrev":"CST"},{"Ticker":"9997.KL","Code":"9997","Name":"PENSONI","Sector":"Consumer Products & Services","Sector Abbrev":"CON"},{"Ticker":"7160.KL","Code":"7160","Name":"PENTA","Sector":"Technology","Sector Abbrev":"TEC"},{"Ticker":"7080.KL","Code":"7080","Name":"PERMAJU","Sector":"Consumer Products & Services","Sector Abbrev":"CON"},{"Ticker":"8311.KL","Code":"8311","Name":"PESONA","Sector":"Construction","Sector Abbrev":"CST"},{"Ticker":"8117.KL","Code":"8117","Name":"PGF","Sector":"Industrial Products & Services","Sector Abbrev":"IND"},{"Ticker":"4464.KL","Code":"4464","Name":"PHB","Sector":"Property","Sector Abbrev":"PRP"},{"Ticker":"7201.KL","Code":"7201","Name":"PICORP","Sector":"Industrial Products & Services","Sector Abbrev":"IND"},{"Ticker":"7163.KL","Code":"7163","Name":"PJBUMI","Sector":"Industrial Products & Services","Sector Abbrev":"IND"},{"Ticker":"7055.KL","Code":"7055","Name":"PLB","Sector":"Property","Sector Abbrev":"PRP"},{"Ticker":"7172.KL","Code":"7172","Name":"PMBTECH","Sector":"Industrial Products & Services","Sector Abbrev":"IND"},{"Ticker":"4081.KL","Code":"4081","Name":"PMCORP","Sector":"Consumer Products & Services","Sector Abbrev":"CON"},{"Ticker":"6637.KL","Code":"6637","Name":"PNEPCB","Sector":"Industrial Products & Services","Sector Abbrev":"IND"},{"Ticker":"7088.KL","Code":"7088","Name":"POHUAT","Sector":"Consumer Products & Services","Sector Abbrev":"CON"},{"Ticker":"8273.KL","Code":"8273","Name":"PPHB","Sector":"Industrial Products & Services","Sector Abbrev":"IND"},{"Ticker":"9873.KL","Code":"9873","Name":"PRESTAR","Sector":"Industrial Products & Services","Sector Abbrev":"IND"},{"Ticker":"7168.KL","Code":"7168","Name":"PRG","Sector":"Consumer Products & Services","Sector Abbrev":"CON"},{"Ticker":"7010.KL","Code":"7010","Name":"PTT","Sector":"Property","Sector Abbrev":"PRP"},{"Ticker":"7134.KL","Code":"7134","Name":"PWF","Sector":"Consumer Products & Services","Sector Abbrev":"CON"},{"Ticker":"7544.KL","Code":"7544","Name":"QUALITY","Sector":"Industrial Products & Services","Sector Abbrev":"IND"},{"Ticker":"7498.KL","Code":"7498","Name":"RALCO","Sector":"Industrial Products & Services","Sector Abbrev":"IND"},{"Ticker":"7232.KL","Code":"7232","Name":"RESINTC","Sector":"Industrial Products & Services","Sector Abbrev":"IND"},{"Ticker":"0037.KL","Code":"0037","Name":"RGB","Sector":"Consumer Products & Services","Sector Abbrev":"CON"},{"Ticker":"9954.KL","Code":"9954","Name":"RGTBHD","Sector":"Industrial Products & Services","Sector Abbrev":"IND"},{"Ticker":"9741.KL","Code":"9741","Name":"ROHAS","Sector":"Industrial Products & Services","Sector Abbrev":"IND"},{"Ticker":"9776.KL","Code":"9776","Name":"SMCAP","Sector":"Consumer Products & Services","Sector Abbrev":"CON"},{"Ticker":"2542.KL","Code":"2542","Name":"RVIEW","Sector":"Plantation","Sector Abbrev":"PLT"},{"Ticker":"8745.KL","Code":"8745","Name":"SFCAP","Sector":"Industrial Products & Services","Sector Abbrev":"IND"},{"Ticker":"9822.KL","Code":"9822","Name":"SAM","Sector":"Industrial Products & Services","Sector Abbrev":"IND"},{"Ticker":"5147.KL","Code":"5147","Name":"SAMCHEM","Sector":"Industrial Products & Services","Sector Abbrev":"IND"},{"Ticker":"7811.KL","Code":"7811","Name":"SAPIND","Sector":"Industrial Products & Services","Sector Abbrev":"IND"},{"Ticker":"4596.KL","Code":"4596","Name":"SAPRES","Sector":"Property","Sector Abbrev":"PRP"},{"Ticker":"2569.KL","Code":"2569","Name":"SBAGAN","Sector":"Plantation","Sector Abbrev":"PLT"},{"Ticker":"7247.KL","Code":"7247","Name":"SCGM","Sector":"Industrial Products & Services","Sector Abbrev":"IND"},{"Ticker":"9237.KL","Code":"9237","Name":"SCIB","Sector":"Industrial Products & Services","Sector Abbrev":"IND"},{"Ticker":"7239.KL","Code":"7239","Name":"SCNWOLF","Sector":"Industrial Products & Services","Sector Abbrev":"IND"},{"Ticker":"4286.KL","Code":"4286","Name":"SEAL","Sector":"Property","Sector Abbrev":"PRP"},{"Ticker":"5145.KL","Code":"5145","Name":"SEALINK","Sector":"Transportation & Logistics","Sector Abbrev":"TRN"},{"Ticker":"5163.KL","Code":"5163","Name":"SEB","Sector":"Industrial Products & Services","Sector Abbrev":"IND"},{"Ticker":"7053.KL","Code":"7053","Name":"SEEHUP","Sector":"Trading Services","Sector Abbrev":"TRD"},{"Ticker":"7180.KL","Code":"7180","Name":"SERNKOU","Sector":"Consumer Products & Services","Sector Abbrev":"CON"},{"Ticker":"5157.KL","Code":"5157","Name":"SG","Sector":"Consumer Products & Services","Sector Abbrev":"CON"},{"Ticker":"4316.KL","Code":"4316","Name":"SHCHAN","Sector":"Plantation","Sector Abbrev":"PLT"},{"Ticker":"7412.KL","Code":"7412","Name":"SHH","Sector":"Consumer Products & Services","Sector Abbrev":"CON"},{"Ticker":"7246.KL","Code":"7246","Name":"SIGN","Sector":"Consumer Products & Services","Sector Abbrev":"CON"},{"Ticker":"5172.KL","Code":"5172","Name":"KSTAR","Sector":"Consumer Products & Services","Sector Abbrev":"CON"},{"Ticker":"9431.KL","Code":"9431","Name":"SJC","Sector":"Telecommunications & Media","Sector Abbrev":"TEL"},{"Ticker":"7115.KL","Code":"7115","Name":"SKBSHUT","Sector":"Industrial Products & Services","Sector Abbrev":"IND"},{"Ticker":"7249.KL","Code":"7249","Name":"SKYGATE","Sector":"Property","Sector Abbrev":"PRP"},{"Ticker":"7248.KL","Code":"7248","Name":"SLP","Sector":"Industrial Products & Services","Sector Abbrev":"IND"},{"Ticker":"4375.KL","Code":"4375","Name":"SMI","Sector":"Property","Sector Abbrev":"PRP"},{"Ticker":"7132.KL","Code":"7132","Name":"SMISCOR","Sector":"Industrial Products & Services","Sector Abbrev":"IND"},{"Ticker":"5242.KL","Code":"5242","Name":"SOLID","Sector":"Consumer Products & Services","Sector Abbrev":"CON"},{"Ticker":"7103.KL","Code":"7103","Name":"SPRITZER","Sector":"Consumer Products & Services","Sector Abbrev":"CON"},{"Ticker":"7207.KL","Code":"7207","Name":"SUCCESS","Sector":"Industrial Products & Services","Sector Abbrev":"IND"},{"Ticker":"0459.KL","Code":"0459","Name":"SUM","Sector":"Industrial Products & Services","Sector Abbrev":"IND"},{"Ticker":"3743.KL","Code":"3743","Name":"SUNSURIA","Sector":"Property","Sector Abbrev":"PRP"},{"Ticker":"7235.KL","Code":"7235","Name":"SUPERLN","Sector":"Industrial Products & Services","Sector Abbrev":"IND"},{"Ticker":"7186.KL","Code":"7186","Name":"SWSCAP","Sector":"Consumer Products & Services","Sector Abbrev":"CON"},{"Ticker":"9717.KL","Code":"9717","Name":"SYCAL","Sector":"Construction","Sector Abbrev":"CST"},{"Ticker":"7211.KL","Code":"7211","Name":"TAFI","Sector":"Consumer Products & Services","Sector Abbrev":"CON"},{"Ticker":"2429.KL","Code":"2429","Name":"TANCO","Sector":"Property","Sector Abbrev":"PRP"},{"Ticker":"5149.KL","Code":"5149","Name":"TAS","Sector":"Transportation & Logistics","Sector Abbrev":"TRN"},{"Ticker":"5140.KL","Code":"5140","Name":"TASCO","Sector":"Trading Services","Sector Abbrev":"TRD"},{"Ticker":"7097.KL","Code":"7097","Name":"TAWIN","Sector":"Industrial Products & Services","Sector Abbrev":"IND"},{"Ticker":"7439.KL","Code":"7439","Name":"TECGUAN","Sector":"Consumer Products & Services","Sector Abbrev":"CON"},{"Ticker":"8966.KL","Code":"8966","Name":"TECHBASE","Sector":"Consumer Products & Services","Sector Abbrev":"CON"},{"Ticker":"5289.KL","Code":"5289","Name":"TECHBND","Sector":"Energy","Sector Abbrev":"ENE"},{"Ticker":"7200.KL","Code":"7200","Name":"TEKSENG","Sector":"Consumer Products & Services","Sector Abbrev":"CON"},{"Ticker":"7252.KL","Code":"7252","Name":"TEOSENG","Sector":"Consumer Products & Services","Sector Abbrev":"CON"},{"Ticker":"8702.KL","Code":"8702","Name":"TEXCHEM","Sector":"Industrial Products & Services","Sector Abbrev":"IND"},{"Ticker":"9369.KL","Code":"9369","Name":"TGL","Sector":"Consumer Products & Services","Sector Abbrev":"CON"},{"Ticker":"7034.KL","Code":"7034","Name":"TGUAN","Sector":"Industrial Products & Services","Sector Abbrev":"IND"},{"Ticker":"9075.KL","Code":"9075","Name":"THETA","Sector":"Technology","Sector Abbrev":"TEC"},{"Ticker":"7889.KL","Code":"7889","Name":"THRIVEN","Sector":"Property","Sector Abbrev":"PRP"},{"Ticker":"7374.KL","Code":"7374","Name":"TIENWAH","Sector":"Industrial Products & Services","Sector Abbrev":"IND"},{"Ticker":"7854.KL","Code":"7854","Name":"TIMWELL","Sector":"Industrial Products & Services","Sector Abbrev":"IND"},{"Ticker":"7230.KL","Code":"7230","Name":"TOMEI","Sector":"Consumer Products & Services","Sector Abbrev":"CON"},{"Ticker":"7285.KL","Code":"7285","Name":"TOMYPAK","Sector":"Industrial Products & Services","Sector Abbrev":"IND"},{"Ticker":"5010.KL","Code":"5010","Name":"TONGHER","Sector":"Industrial Products & Services","Sector Abbrev":"IND"},{"Ticker":"7173.KL","Code":"7173","Name":"TOYOVEN","Sector":"Industrial Products & Services","Sector Abbrev":"IND"},{"Ticker":"7176.KL","Code":"7176","Name":"TPC","Sector":"Consumer Products & Services","Sector Abbrev":"CON"},{"Ticker":"0118.KL","Code":"0118","Name":"TRIVE","Sector":"Technology","Sector Abbrev":"TEC"},{"Ticker":"5042.KL","Code":"5042","Name":"TSRCAP","Sector":"Construction","Sector Abbrev":"CST"},{"Ticker":"5167.KL","Code":"5167","Name":"TURBO","Sector":"Industrial Products & Services","Sector Abbrev":"IND"},{"Ticker":"4359.KL","Code":"4359","Name":"TURIYA","Sector":"Technology","Sector Abbrev":"TEC"},{"Ticker":"7079.KL","Code":"7079","Name":"TWL","Sector":"Property","Sector Abbrev":"PRP"},{"Ticker":"7145.KL","Code":"7145","Name":"TXCD","Sector":"Construction","Sector Abbrev":"CST"},{"Ticker":"7133.KL","Code":"7133","Name":"ULICORP","Sector":"Industrial Products & Services","Sector Abbrev":"IND"},{"Ticker":"7137.KL","Code":"7137","Name":"UMS","Sector":"Industrial Products & Services","Sector Abbrev":"IND"},{"Ticker":"7227.KL","Code":"7227","Name":"UMSNGB","Sector":"Industrial Products & Services","Sector Abbrev":"IND"},{"Ticker":"7091.KL","Code":"7091","Name":"UNIMECH","Sector":"Industrial Products & Services","Sector Abbrev":"IND"},{"Ticker":"7757.KL","Code":"7757","Name":"UPA","Sector":"Consumer Products & Services","Sector Abbrev":"CON"},{"Ticker":"5006.KL","Code":"5006","Name":"VARIA","Sector":"Construction","Sector Abbrev":"CST"},{"Ticker":"7165.KL","Code":"7165","Name":"VELOCITY","Sector":"Industrial Products & Services","Sector Abbrev":"IND"},{"Ticker":"7070.KL","Code":"7070","Name":"VIZIONE","Sector":"Construction","Sector Abbrev":"CST"},{"Ticker":"6963.KL","Code":"6963","Name":"VS","Sector":"Industrial Products & Services","Sector Abbrev":"IND"},{"Ticker":"5162.KL","Code":"5162","Name":"VSTECS","Sector":"Technology","Sector Abbrev":"TEC"},{"Ticker":"7203.KL","Code":"7203","Name":"WANGZNG","Sector":"Consumer Products & Services","Sector Abbrev":"CON"},{"Ticker":"5016.KL","Code":"5016","Name":"WARISAN","Sector":"Consumer Products & Services","Sector Abbrev":"CON"},{"Ticker":"7226.KL","Code":"7226","Name":"WATTA","Sector":"Industrial Products & Services","Sector Abbrev":"IND"},{"Ticker":"8176.KL","Code":"8176","Name":"WAVEFRNT","Sector":"Industrial Products & Services","Sector Abbrev":"IND"},{"Ticker":"0008.KL","Code":"0008","Name":"WILLOW","Sector":"Technology","Sector Abbrev":"TEC"},{"Ticker":"7050.KL","Code":"7050","Name":"WONG","Sector":"Industrial Products & Services","Sector Abbrev":"IND"},{"Ticker":"7025.KL","Code":"7025","Name":"WOODLAN","Sector":"Industrial Products & Services","Sector Abbrev":"IND"},{"Ticker":"5156.KL","Code":"5156","Name":"XDL","Sector":"Consumer Products & Services","Sector Abbrev":"CON"},{"Ticker":"7043.KL","Code":"7043","Name":"XIN","Sector":"Industrial Products & Services","Sector Abbrev":"IND"},{"Ticker":"7121.KL","Code":"7121","Name":"XL","Sector":"Consumer Products & Services","Sector Abbrev":"CON"},{"Ticker":"7003.KL","Code":"7003","Name":"YG","Sector":"Property","Sector Abbrev":"PRP"},{"Ticker":"5048.KL","Code":"5048","Name":"YB","Sector":"Industrial Products & Services","Sector Abbrev":"IND"},{"Ticker":"7014.KL","Code":"7014","Name":"YLI","Sector":"Industrial Products & Services","Sector Abbrev":"IND"},{"Ticker":"5159.KL","Code":"5159","Name":"YOCB","Sector":"Consumer Products & Services","Sector Abbrev":"CON"},{"Ticker":"7066.KL","Code":"7066","Name":"YONGTAI","Sector":"Property","Sector Abbrev":"PRP"},{"Ticker":"7178.KL","Code":"7178","Name":"YSPSAH","Sector":"Health Care","Sector Abbrev":"HLT"},{"Ticker":"7028.KL","Code":"7028","Name":"ZECON","Sector":"Construction","Sector Abbrev":"CST"}]